typehintwhl/__init__.py
typehintwhl/__init__.pyi
typehintwhl/__main__.py
typehintwhl/build.py
typehintwhl/build.pyi
typehintwhl/cli.py
typehintwhl/common.py
typehintwhl/common.pyi
typehintwhl/config.py
typehintwhl/config.pyi
typehintwhl/distutils.pyi
typehintwhl/exception.py
typehintwhl/log.py
typehintwhl/setuptools.pyi
typehintwhl/command/build_stub.py
typehintwhl/command/build_stub.pyi
typehintwhl-0.0.1.dist-info/METADATA
typehintwhl-0.0.1.dist-info/WHEEL
typehintwhl-0.0.1.dist-info/top_level.txt
typehintwhl-0.0.1.dist-info/RECORD
